CheckmarxPythonSDK/__init__.py
CheckmarxPythonSDK/__version__.py
CheckmarxPythonSDK/api_client.py
CheckmarxPythonSDK/configuration.py
CheckmarxPythonSDK/CxAccessControl/AccessControl.py
CheckmarxPythonSDK/CxAccessControl/__init__.py
CheckmarxPythonSDK/CxAccessControl/accesscontrol/__init__.py
CheckmarxPythonSDK/CxAccessControl/accesscontrol/dto/AuthenticationProvider.py
CheckmarxPythonSDK/CxAccessControl/accesscontrol/dto/Configuration.py
CheckmarxPythonSDK/CxAccessControl/accesscontrol/dto/LDAPGroup.py
CheckmarxPythonSDK/CxAccessControl/accesscontrol/dto/LDAPGroupAndRoleMappingDetail.py
CheckmarxPythonSDK/CxAccessControl/accesscontrol/dto/LDAPRoleMapping.py
CheckmarxPythonSDK/CxAccessControl/accesscontrol/dto/LDAPServer.py
CheckmarxPythonSDK/CxAccessControl/accesscontrol/dto/LDAPTeamMapping.py
CheckmarxPythonSDK/CxAccessControl/accesscontrol/dto/MyProfile.py
CheckmarxPythonSDK/CxAccessControl/accesscontrol/dto/OIDCClient.py
CheckmarxPythonSDK/CxAccessControl/accesscontrol/dto/Permission.py
CheckmarxPythonSDK/CxAccessControl/accesscontrol/dto/Role.py
CheckmarxPythonSDK/CxAccessControl/accesscontrol/dto/SAMLIdentityProvider.py
CheckmarxPythonSDK/CxAccessControl/accesscontrol/dto/SAMLRoleMapping.py
CheckmarxPythonSDK/CxAccessControl/accesscontrol/dto/SAMLServiceProvider.py
CheckmarxPythonSDK/CxAccessControl/accesscontrol/dto/SAMLTeamMapping.py
CheckmarxPythonSDK/CxAccessControl/accesscontrol/dto/SMTPSetting.py
CheckmarxPythonSDK/CxAccessControl/accesscontrol/dto/ServiceProvider.py
CheckmarxPythonSDK/CxAccessControl/accesscontrol/dto/SystemLocale.py
CheckmarxPythonSDK/CxAccessControl/accesscontrol/dto/Team.py
CheckmarxPythonSDK/CxAccessControl/accesscontrol/dto/User.py
CheckmarxPythonSDK/CxAccessControl/accesscontrol/dto/WindowsDomain.py
CheckmarxPythonSDK/CxAccessControl/accesscontrol/dto/__init__.py
CheckmarxPythonSDK/CxODataApiSDK/ProjectsODataAPI.py
CheckmarxPythonSDK/CxODataApiSDK/ResultsODataAPI.py
CheckmarxPythonSDK/CxODataApiSDK/ScansODataAPI.py
checkmarxpythonsdk-1.6.9.dist-info/licenses/LICENSE
checkmarxpythonsdk-1.6.9.dist-info/METADATA
checkmarxpythonsdk-1.6.9.dist-info/WHEEL
checkmarxpythonsdk-1.6.9.dist-info/top_level.txt
checkmarxpythonsdk-1.6.9.dist-info/RECORD
