Metadata-Version: 2.4
Name: CheckmarxPythonSDK
Version: 1.6.9
Summary: Checkmarx Python SDK
Home-page: https://github.com/checkmarx-ts/checkmarx-python-sdk
Author: Happy Yang
Author-email: happy.yang@checkmarx.com
Classifier: Programming Language :: Python :: 3
Classifier: Programming Language :: Python :: 3.7
Classifier: License :: OSI Approved :: GNU General Public License v3 (GPLv3)
Classifier: Operating System :: OS Independent
Classifier: Programming Language :: Python :: Implementation :: CPython
Classifier: Programming Language :: Python :: Implementation :: PyPy
Requires-Python: !=3.0.*, !=3.1.*, !=3.2.*, !=3.3.*, !=3.4.*, >=3.7
License-File: LICENSE
Requires-Dist: requests>=2.13.0
Requires-Dist: requests-toolbelt>=0.9.1
Requires-Dist: zeep>=4.1.0
Requires-Dist: Deprecated>=1.2.13
Requires-Dist: inflection>=0.5.1
Requires-Dist: typing-extensions>=4.15.0
Provides-Extra: dotenv
Requires-Dist: python-dotenv; extra == "dotenv"
Provides-Extra: dev
Requires-Dist: pytest; extra == "dev"
Requires-Dist: coverage; extra == "dev"
Dynamic: author
Dynamic: author-email
Dynamic: classifier
Dynamic: description
Dynamic: description-content-type
Dynamic: home-page
Dynamic: license-file
Dynamic: provides-extra
Dynamic: requires-dist
Dynamic: requires-python
Dynamic: summary
